fds/__init__.py
fds/sdk/__init__.py
fds/sdk/FactSetEntity/__init__.py
fds/sdk/FactSetEntity/api_client.py
fds/sdk/FactSetEntity/configuration.py
fds/sdk/FactSetEntity/exceptions.py
fds/sdk/FactSetEntity/model_utils.py
fds/sdk/FactSetEntity/rest.py
fds/sdk/FactSetEntity/api/__init__.py
fds/sdk/FactSetEntity/api/entity_reference_api.py
fds/sdk/FactSetEntity/api/entity_reference_chinese_api.py
fds/sdk/FactSetEntity/api/entity_securities_api.py
fds/sdk/FactSetEntity/api/entity_structure_api.py
fds/sdk/FactSetEntity/api/historical_credit_parent_api.py
fds/sdk/FactSetEntity/apis/__init__.py
fds/sdk/FactSetEntity/model/__init__.py
fds/sdk/FactSetEntity/model/active.py
fds/sdk/FactSetEntity/model/credit_parent.py
fds/sdk/FactSetEntity/model/credit_parent_request.py
fds/sdk/FactSetEntity/model/credit_parent_response.py
fds/sdk/FactSetEntity/model/entity_reference.py
fds/sdk/FactSetEntity/model/entity_reference_chi.py
fds/sdk/FactSetEntity/model/entity_reference_chi_request.py
fds/sdk/FactSetEntity/model/entity_reference_chi_response.py
fds/sdk/FactSetEntity/model/entity_reference_request.py
fds/sdk/FactSetEntity/model/entity_reference_response.py
fds/sdk/FactSetEntity/model/entity_securities.py
fds/sdk/FactSetEntity/model/entity_securities_request.py
fds/sdk/FactSetEntity/model/entity_securities_response.py
fds/sdk/FactSetEntity/model/entity_structure.py
fds/sdk/FactSetEntity/model/entity_structure_request.py
fds/sdk/FactSetEntity/model/entity_structure_response.py
fds/sdk/FactSetEntity/model/error_response.py
fds/sdk/FactSetEntity/model/error_response_sub_errors.py
fds/sdk/FactSetEntity/model/hcp_ids.py
fds/sdk/FactSetEntity/model/ids.py
fds/sdk/FactSetEntity/model/ids_chi.py
fds/sdk/FactSetEntity/model/security_type.py
fds/sdk/FactSetEntity/model/structure_ids.py
fds/sdk/FactSetEntity/model/ultimate_entity_structure_request.py
fds/sdk/FactSetEntity/model/ultimate_entity_structure_response.py
fds/sdk/FactSetEntity/model/utlimate_entity_structure.py
fds_sdk_factsetentity-1.3.0.dist-info/licenses/LICENSE
fds_sdk_factsetentity-1.3.0.dist-info/METADATA
fds_sdk_factsetentity-1.3.0.dist-info/WHEEL
fds_sdk_factsetentity-1.3.0.dist-info/top_level.txt
fds_sdk_factsetentity-1.3.0.dist-info/RECORD
